odoo10_addon_account_netting-10.0.1.0.0-py2.7-nspkg.pth
odoo/addons/account_netting/README.rst
odoo/addons/account_netting/__init__.py
odoo/addons/account_netting/__manifest__.py
odoo/addons/account_netting/i18n/es.po
odoo/addons/account_netting/static/description/icon.png
odoo/addons/account_netting/tests/__init__.py
odoo/addons/account_netting/tests/test_account_netting.py
odoo/addons/account_netting/wizards/__init__.py
odoo/addons/account_netting/wizards/account_move_make_netting.py
odoo/addons/account_netting/wizards/account_move_make_netting_view.xml
odoo10_addon_account_netting-10.0.1.0.0.dist-info/DESCRIPTION.rst
odoo10_addon_account_netting-10.0.1.0.0.dist-info/METADATA
odoo10_addon_account_netting-10.0.1.0.0.dist-info/RECORD
odoo10_addon_account_netting-10.0.1.0.0.dist-info/WHEEL
odoo10_addon_account_netting-10.0.1.0.0.dist-info/metadata.json
odoo10_addon_account_netting-10.0.1.0.0.dist-info/namespace_packages.txt
odoo10_addon_account_netting-10.0.1.0.0.dist-info/top_level.txt
